RotateScreen/0.py
RotateScreen/270.py
RotateScreen/__init__.py
Rotater-0.0.2.dist-info/LICENSE
Rotater-0.0.2.dist-info/METADATA
Rotater-0.0.2.dist-info/WHEEL
Rotater-0.0.2.dist-info/top_level.txt
Rotater-0.0.2.dist-info/RECORD
