Metadata-Version: 2.1
Name: Rotater
Version: 0.0.2
Summary: Lakshay
Home-page: UNKNOWN
Author: Lakshay
Author-email: sharmalakshay0208@gmail.com
License: UNKNOWN
Keywords: hacking,math,mathematics,python tutorial,Lakshay Sharma
Platform: UNKNOWN
Classifier: Development Status :: 1 - Planning
Classifier: Intended Audience :: Developers
Classifier: Programming Language :: Python
Classifier: Operating System :: Unix
Classifier: Operating System :: MacOS :: MacOS X
Classifier: Operating System :: Microsoft :: Windows
Requires-Dist: rotatescreen
